{
  "gitSyncId": "66b26a59a409ab5ad1e6bdbf_cae4e098-055f-47c9-92af-36158bda1626",
  "id": "Page1_JSModule126",
  "moduleUUID": "2a96bf68-cbf3-451e-869e-103f78d769f9",
  "packageUUID": "6dad4585-7894-4100-9b0d-3794b1285eab",
  "type": "JS_MODULE",
  "unpublishedModuleInstance": {
    "contextType": "PAGE",
    "inputs": {
      "myFun1": "[\"{{1}}\"]",
      "myFun2": "[]"
    },
    "moduleInputs": {
      "sjamfjupyd": {},
      "umlxaagdxc": {}
    },
    "name": "JSModule126",
    "pageId": "Page1",
    "version": "0.0.4"
  }
}