{
  "gitSyncId": "66b27325a409ab5ad1e6c456_d3679ff7-5477-4050-81cd-a76a84b648b1",
  "id": "Page1__$JSModule125aaa$_JSModule1.myFun1",
  "isPublic": true,
  "moduleInstanceId": "Page1_JSModule125aaa",
  "pluginId": "js-plugin",
  "pluginType": "JS",
  "rootModuleInstanceId": "Page1_JSModule125aaa",
  "unpublishedAction": {
    "clientSideExecution": true,
    "collectionId": "Page1__$JSModule125aaa$_JSModule1",
    "confirmBeforeExecute": false,
    "contextType": "PAGE",
    "datasource": {
      "isAutoGenerated": false,
      "name": "UNUSED_DATASOURCE",
      "pluginId": "js-plugin"
    },
    "executeOnLoad": false,
    "fullyQualifiedName": "_$JSModule125aaa$_JSModule1.myFun1",
    "name": "myFun1",
    "pageId": "Page1",
    "userSetOnLoad": false
  }
}